face_recognition/__init__.py
face_recognition/models/__init__.py
face_recognition/models/arcnet.py
face_recognition/models/retina.py
face_recognition/utils/__init__.py
face_recognition/utils/tools.py
green_face_recognition-0.1.6.dist-info/LICENSE
green_face_recognition-0.1.6.dist-info/METADATA
green_face_recognition-0.1.6.dist-info/WHEEL
green_face_recognition-0.1.6.dist-info/top_level.txt
green_face_recognition-0.1.6.dist-info/RECORD
