Metadata-Version: 2.1
Name: green-face-recognition
Version: 0.1.6
Summary: HungLV package
Home-page: https://github.com/leviethung2103/greenlab_ai_utils
Author: Hung LV
Author-email: leviethung1280@gmail.com
License: MIT
Platform: UNKNOWN
Classifier: Programming Language :: Python :: 3
Classifier: License :: OSI Approved :: MIT License
Classifier: Operating System :: OS Independent
Requires-Python: >=3.6
